{
    "Insertion-1ppm": {
        "Detections": [
            {
                "timestamp": 1608126372.203988,
                "frequency": 5009876.260000001,
                "resistance": 391.89799999999997,
                "period": [
                    0,
                    0
                ],
                "time": "",
                "severity": "severe",
                "detector": "Mean-shift"
            }
        ],
        "Anomalies": [
            {
                "Start": 1608125974.41765,
                "End": 1608126904.1467898
            }
        ],
        "Number of detections": 1,
        "True Positives": [
            {
                "timestamp": 1608126372.203988,
                "frequency": 5009876.260000001,
                "resistance": 391.89799999999997,
                "period": [
                    0,
                    0
                ],
                "time": "",
                "severity": "severe",
                "detector": "Mean-shift"
            }
        ],
        "False Negatives": [],
        "Number of True Positives": 1,
        "Number of False Positives": 0,
        "Number of False Negatives": 0,
        "Number of True Negatives": 1,
        "Total Detection Time": 38.909635066986084,
        "Recall": 1.0,
        "Path": "/home/kimino/soft/qcm-detector/data/tests/Insertion-1ppm_chosen.csv"
    },
    "Long-Insertion-10ppm": {
        "Detections": [],
        "Anomalies": [
            {
                "Start": 1605640325.882498,
                "End": 1605642864.993002
            }
        ],
        "Number of detections": 0,
        "True Positives": [],
        "False Negatives": [
            {
                "Start": 1605640325.882498,
                "End": 1605642864.993002
            }
        ],
        "Number of True Positives": 0,
        "Number of False Positives": 0,
        "Number of False Negatives": 1,
        "Number of True Negatives": 0,
        "Total Detection Time": 304.6821253299713,
        "Recall": 0.0,
        "Path": "/home/kimino/soft/qcm-detector/data/tests/Long-Insertion-10ppm_chosen.csv"
    },
    "Hard-Water-4": {
        "Detections": [
            {
                "timestamp": 1611867961.20335,
                "frequency": 5009825.15,
                "resistance": 408.195,
                "period": [
                    0,
                    0
                ],
                "time": "",
                "severity": "severe",
                "detector": "Expo-predict"
            }
        ],
        "Anomalies": [],
        "Number of detections": 1,
        "True Positives": [],
        "False Negatives": [],
        "Number of True Positives": 0,
        "Number of False Positives": 1,
        "Number of False Negatives": 0,
        "Number of True Negatives": 0,
        "Total Detection Time": 136.25777912139893,
        "Recall": 0,
        "Path": "/home/kimino/soft/qcm-detector/data/tests/Hard-Water-4_chosen.csv"
    },
    "Hard-0": {
        "Detections": [],
        "Anomalies": [
            {
                "Start": 1611594185.5070772,
                "End": 1611595975.166763
            }
        ],
        "Number of detections": 0,
        "True Positives": [],
        "False Negatives": [
            {
                "Start": 1611594185.5070772,
                "End": 1611595975.166763
            }
        ],
        "Number of True Positives": 0,
        "Number of False Positives": 0,
        "Number of False Negatives": 1,
        "Number of True Negatives": 0,
        "Total Detection Time": 86.86181569099426,
        "Recall": 0.0,
        "Path": "/home/kimino/soft/qcm-detector/data/tests/Hard-0.1ppm_chosen.csv"
    },
    "Long-Insertion-5ppm": {
        "Detections": [],
        "Anomalies": [
            {
                "Start": 1605720216.904716,
                "End": 1605722213.19387
            }
        ],
        "Number of detections": 0,
        "True Positives": [],
        "False Negatives": [
            {
                "Start": 1605720216.904716,
                "End": 1605722213.19387
            }
        ],
        "Number of True Positives": 0,
        "Number of False Positives": 0,
        "Number of False Negatives": 1,
        "Number of True Negatives": 0,
        "Total Detection Time": 237.1968059539795,
        "Recall": 0.0,
        "Path": "/home/kimino/soft/qcm-detector/data/tests/Long-Insertion-5ppm_chosen.csv"
    },
    "Hard-1ppm": {
        "Detections": [
            {
                "timestamp": 1611602801.8421683,
                "frequency": 5009853.700000001,
                "resistance": 400.995,
                "period": [
                    0,
                    0
                ],
                "time": "",
                "severity": "severe",
                "detector": "Expo-predict"
            },
            {
                "timestamp": 1611602871.8413668,
                "frequency": 5009847.8,
                "resistance": 437.58500000000004,
                "period": [
                    0,
                    0
                ],
                "time": "",
                "severity": "severe",
                "detector": "Expo-predict"
            }
        ],
        "Anomalies": [
            {
                "Start": 1611602758.341238,
                "End": 1611604571.272348
            }
        ],
        "Number of detections": 2,
        "True Positives": [
            {
                "timestamp": 1611602801.8421683,
                "frequency": 5009853.700000001,
                "resistance": 400.995,
                "period": [
                    0,
                    0
                ],
                "time": "",
                "severity": "severe",
                "detector": "Expo-predict"
            },
            {
                "timestamp": 1611602871.8413668,
                "frequency": 5009847.8,
                "resistance": 437.58500000000004,
                "period": [
                    0,
                    0
                ],
                "time": "",
                "severity": "severe",
                "detector": "Expo-predict"
            }
        ],
        "False Negatives": [],
        "Number of True Positives": 2,
        "Number of False Positives": 0,
        "Number of False Negatives": 0,
        "Number of True Negatives": 1,
        "Total Detection Time": 93.3150999546051,
        "Recall": 1.0,
        "Path": "/home/kimino/soft/qcm-detector/data/tests/Hard-1ppm_chosen.csv"
    },
    "Swell-10ppm": {
        "Detections": [
            {
                "timestamp": 1611150031.3458233,
                "frequency": 5009954.833333333,
                "resistance": 446.59,
                "period": [
                    0,
                    0
                ],
                "time": "",
                "severity": "severe",
                "detector": "Expo-predict"
            },
            {
                "timestamp": 1611150221.3488178,
                "frequency": 5009959.766666667,
                "resistance": 453.8866666666666,
                "period": [
                    0,
                    0
                ],
                "time": "",
                "severity": "severe",
                "detector": "Mean-shift"
            },
            {
                "timestamp": 1611150821.3493233,
                "frequency": 5009952.933333334,
                "resistance": 456.30333333333334,
                "period": [
                    0,
                    0
                ],
                "time": "",
                "severity": "severe",
                "detector": "Mean-shift"
            }
        ],
        "Anomalies": [
            {
                "Start": 1611149997.343408,
                "End": 1611151008.38065
            }
        ],
        "Number of detections": 3,
        "True Positives": [
            {
                "timestamp": 1611150031.3458233,
                "frequency": 5009954.833333333,
                "resistance": 446.59,
                "period": [
                    0,
                    0
                ],
                "time": "",
                "severity": "severe",
                "detector": "Expo-predict"
            },
            {
                "timestamp": 1611150221.3488178,
                "frequency": 5009959.766666667,
                "resistance": 453.8866666666666,
                "period": [
                    0,
                    0
                ],
                "time": "",
                "severity": "severe",
                "detector": "Mean-shift"
            },
            {
                "timestamp": 1611150821.3493233,
                "frequency": 5009952.933333334,
                "resistance": 456.30333333333334,
                "period": [
                    0,
                    0
                ],
                "time": "",
                "severity": "severe",
                "detector": "Mean-shift"
            }
        ],
        "False Negatives": [],
        "Number of True Positives": 3,
        "Number of False Positives": 0,
        "Number of False Negatives": 0,
        "Number of True Negatives": 1,
        "Total Detection Time": 35.99037957191467,
        "Recall": 1.0,
        "Path": "/home/kimino/soft/qcm-detector/data/tests/Swell-10ppm_chosen.csv"
    },
    "Insertion-5ppm": {
        "Detections": [
            {
                "timestamp": 1608129921.1155746,
                "frequency": 5009813.333333333,
                "resistance": 399.57,
                "period": [
                    0,
                    0
                ],
                "time": "",
                "severity": "severe",
                "detector": "Mean-shift"
            },
            {
                "timestamp": 1608130521.6275072,
                "frequency": 5009803.25,
                "resistance": 400.5675,
                "period": [
                    0,
                    0
                ],
                "time": "",
                "severity": "severe",
                "detector": "Mean-shift"
            }
        ],
        "Anomalies": [
            {
                "Start": 1608129581.928116,
                "End": 1608130536.1278238
            }
        ],
        "Number of detections": 2,
        "True Positives": [
            {
                "timestamp": 1608129921.1155746,
                "frequency": 5009813.333333333,
                "resistance": 399.57,
                "period": [
                    0,
                    0
                ],
                "time": "",
                "severity": "severe",
                "detector": "Mean-shift"
            },
            {
                "timestamp": 1608130521.6275072,
                "frequency": 5009803.25,
                "resistance": 400.5675,
                "period": [
                    0,
                    0
                ],
                "time": "",
                "severity": "severe",
                "detector": "Mean-shift"
            }
        ],
        "False Negatives": [],
        "Number of True Positives": 2,
        "Number of False Positives": 0,
        "Number of False Negatives": 0,
        "Number of True Negatives": 1,
        "Total Detection Time": 34.29369282722473,
        "Recall": 1.0,
        "Path": "/home/kimino/soft/qcm-detector/data/tests/Insertion-5ppm_chosen.csv"
    },
    "Insertion-30ppm": {
        "Detections": [
            {
                "timestamp": 1608133701.7469983,
                "frequency": 5009779.35,
                "resistance": 407.7175,
                "period": [
                    0,
                    0
                ],
                "time": "",
                "severity": "severe",
                "detector": "Mean-shift"
            },
            {
                "timestamp": 1608134302.1506915,
                "frequency": 5009764.26,
                "resistance": 411.55600000000004,
                "period": [
                    0,
                    0
                ],
                "time": "",
                "severity": "severe",
                "detector": "Mean-shift"
            }
        ],
        "Anomalies": [
            {
                "Start": 1608133463.2444532,
                "End": 1608134610.15019
            }
        ],
        "Number of detections": 2,
        "True Positives": [
            {
                "timestamp": 1608133701.7469983,
                "frequency": 5009779.35,
                "resistance": 407.7175,
                "period": [
                    0,
                    0
                ],
                "time": "",
                "severity": "severe",
                "detector": "Mean-shift"
            },
            {
                "timestamp": 1608134302.1506915,
                "frequency": 5009764.26,
                "resistance": 411.55600000000004,
                "period": [
                    0,
                    0
                ],
                "time": "",
                "severity": "severe",
                "detector": "Mean-shift"
            }
        ],
        "False Negatives": [],
        "Number of True Positives": 2,
        "Number of False Positives": 0,
        "Number of False Negatives": 0,
        "Number of True Negatives": 1,
        "Total Detection Time": 42.309473514556885,
        "Recall": 1.0,
        "Path": "/home/kimino/soft/qcm-detector/data/tests/Insertion-30ppm_chosen.csv"
    },
    "Hard-H20-Tap": {
        "Detections": [
            {
                "timestamp": 1611265051.65769,
                "frequency": 5009836.475,
                "resistance": 431.60249999999996,
                "period": [
                    0,
                    0
                ],
                "time": "",
                "severity": "severe",
                "detector": "Expo-predict"
            },
            {
                "timestamp": 1611265251.6856074,
                "frequency": 5009898.9,
                "resistance": 416.7075,
                "period": [
                    0,
                    0
                ],
                "time": "",
                "severity": "severe",
                "detector": "Mean-shift"
            },
            {
                "timestamp": 1611265851.7648377,
                "frequency": 5009892.0,
                "resistance": 417.51,
                "period": [
                    0,
                    0
                ],
                "time": "",
                "severity": "severe",
                "detector": "Mean-shift"
            }
        ],
        "Anomalies": [
            {
                "Start": 1611264958.1492999,
                "End": 1611266698.3917902
            }
        ],
        "Number of detections": 3,
        "True Positives": [
            {
                "timestamp": 1611265051.65769,
                "frequency": 5009836.475,
                "resistance": 431.60249999999996,
                "period": [
                    0,
                    0
                ],
                "time": "",
                "severity": "severe",
                "detector": "Expo-predict"
            },
            {
                "timestamp": 1611265251.6856074,
                "frequency": 5009898.9,
                "resistance": 416.7075,
                "period": [
                    0,
                    0
                ],
                "time": "",
                "severity": "severe",
                "detector": "Mean-shift"
            },
            {
                "timestamp": 1611265851.7648377,
                "frequency": 5009892.0,
                "resistance": 417.51,
                "period": [
                    0,
                    0
                ],
                "time": "",
                "severity": "severe",
                "detector": "Mean-shift"
            }
        ],
        "False Negatives": [],
        "Number of True Positives": 3,
        "Number of False Positives": 0,
        "Number of False Negatives": 0,
        "Number of True Negatives": 1,
        "Total Detection Time": 99.14392471313477,
        "Recall": 1.0,
        "Path": "/home/kimino/soft/qcm-detector/data/tests/Hard-H20-Tap_chosen.csv"
    },
    "Hard-5ppm": {
        "Detections": [
            {
                "timestamp": 1611260962.45576,
                "frequency": 5009841.46,
                "resistance": 423.052,
                "period": [
                    0,
                    0
                ],
                "time": "",
                "severity": "severe",
                "detector": "Expo-predict"
            },
            {
                "timestamp": 1611261022.4564402,
                "frequency": 5009910.62,
                "resistance": 457.90199999999993,
                "period": [
                    0,
                    0
                ],
                "time": "",
                "severity": "severe",
                "detector": "Expo-predict"
            },
            {
                "timestamp": 1611261082.45748,
                "frequency": 5009914.12,
                "resistance": 460.43,
                "period": [
                    0,
                    0
                ],
                "time": "",
                "severity": "severe",
                "detector": "Mean-shift"
            },
            {
                "timestamp": 1611261492.46422,
                "frequency": 5009917.68,
                "resistance": 465.03599999999994,
                "period": [
                    0,
                    0
                ],
                "time": "",
                "severity": "severe",
                "detector": "Mean-shift"
            }
        ],
        "Anomalies": [
            {
                "Start": 1611260899.4550998,
                "End": 1611261988.471
            }
        ],
        "Number of detections": 4,
        "True Positives": [
            {
                "timestamp": 1611260962.45576,
                "frequency": 5009841.46,
                "resistance": 423.052,
                "period": [
                    0,
                    0
                ],
                "time": "",
                "severity": "severe",
                "detector": "Expo-predict"
            },
            {
                "timestamp": 1611261022.4564402,
                "frequency": 5009910.62,
                "resistance": 457.90199999999993,
                "period": [
                    0,
                    0
                ],
                "time": "",
                "severity": "severe",
                "detector": "Expo-predict"
            },
            {
                "timestamp": 1611261082.45748,
                "frequency": 5009914.12,
                "resistance": 460.43,
                "period": [
                    0,
                    0
                ],
                "time": "",
                "severity": "severe",
                "detector": "Mean-shift"
            },
            {
                "timestamp": 1611261492.46422,
                "frequency": 5009917.68,
                "resistance": 465.03599999999994,
                "period": [
                    0,
                    0
                ],
                "time": "",
                "severity": "severe",
                "detector": "Mean-shift"
            }
        ],
        "False Negatives": [],
        "Number of True Positives": 4,
        "Number of False Positives": 0,
        "Number of False Negatives": 0,
        "Number of True Negatives": 1,
        "Total Detection Time": 48.711092472076416,
        "Recall": 1.0,
        "Path": "/home/kimino/soft/qcm-detector/data/tests/Hard-5ppm_chosen.csv"
    },
    "Hard-Water-5": {
        "Detections": [
            {
                "timestamp": 1611864401.7106667,
                "frequency": 5009825.166666667,
                "resistance": 413.17,
                "period": [
                    0,
                    0
                ],
                "time": "",
                "severity": "severe",
                "detector": "Expo-predict"
            }
        ],
        "Anomalies": [],
        "Number of detections": 1,
        "True Positives": [],
        "False Negatives": [],
        "Number of True Positives": 0,
        "Number of False Positives": 1,
        "Number of False Negatives": 0,
        "Number of True Negatives": 0,
        "Total Detection Time": 168.49233317375183,
        "Recall": 0,
        "Path": "/home/kimino/soft/qcm-detector/data/tests/Hard-Water-5_chosen.csv"
    },
    "Hard-5ppm-1": {
        "Detections": [
            {
                "timestamp": 1611610421.2782998,
                "frequency": 5009773.1,
                "resistance": 417.71000000000004,
                "period": [
                    0,
                    0
                ],
                "time": "",
                "severity": "severe",
                "detector": "Expo-predict"
            },
            {
                "timestamp": 1611610651.2781498,
                "frequency": 5009829.8,
                "resistance": 458.47,
                "period": [
                    0,
                    0
                ],
                "time": "",
                "severity": "severe",
                "detector": "Mean-shift"
            },
            {
                "timestamp": 1611611031.2797,
                "frequency": 5009828.3,
                "resistance": 463.09000000000003,
                "period": [
                    0,
                    0
                ],
                "time": "",
                "severity": "severe",
                "detector": "Mean-shift"
            },
            {
                "timestamp": 1611611631.27985,
                "frequency": 5009828.3,
                "resistance": 464.655,
                "period": [
                    0,
                    0
                ],
                "time": "",
                "severity": "severe",
                "detector": "Mean-shift"
            }
        ],
        "Anomalies": [
            {
                "Start": 1611610396.7789,
                "End": 1611612449.7859998
            }
        ],
        "Number of detections": 4,
        "True Positives": [
            {
                "timestamp": 1611610421.2782998,
                "frequency": 5009773.1,
                "resistance": 417.71000000000004,
                "period": [
                    0,
                    0
                ],
                "time": "",
                "severity": "severe",
                "detector": "Expo-predict"
            },
            {
                "timestamp": 1611610651.2781498,
                "frequency": 5009829.8,
                "resistance": 458.47,
                "period": [
                    0,
                    0
                ],
                "time": "",
                "severity": "severe",
                "detector": "Mean-shift"
            },
            {
                "timestamp": 1611611031.2797,
                "frequency": 5009828.3,
                "resistance": 463.09000000000003,
                "period": [
                    0,
                    0
                ],
                "time": "",
                "severity": "severe",
                "detector": "Mean-shift"
            },
            {
                "timestamp": 1611611631.27985,
                "frequency": 5009828.3,
                "resistance": 464.655,
                "period": [
                    0,
                    0
                ],
                "time": "",
                "severity": "severe",
                "detector": "Mean-shift"
            }
        ],
        "False Negatives": [],
        "Number of True Positives": 4,
        "Number of False Positives": 0,
        "Number of False Negatives": 0,
        "Number of True Negatives": 1,
        "Total Detection Time": 71.58667850494385,
        "Recall": 1.0,
        "Path": "/home/kimino/soft/qcm-detector/data/tests/Hard-5ppm-1_chosen.csv"
    },
    "Insertion-50ppm": {
        "Detections": [
            {
                "timestamp": 1608135820.9868429,
                "frequency": 5009730.0,
                "resistance": 408.34,
                "period": [
                    0,
                    0
                ],
                "time": "",
                "severity": "severe",
                "detector": "Expo-predict"
            },
            {
                "timestamp": 1608135900.984927,
                "frequency": 5009716.9,
                "resistance": 414.35,
                "period": [
                    0,
                    0
                ],
                "time": "",
                "severity": "severe",
                "detector": "Mean-shift"
            },
            {
                "timestamp": 1608136510.6807976,
                "frequency": 5009723.7,
                "resistance": 416.92,
                "period": [
                    0,
                    0
                ],
                "time": "",
                "severity": "severe",
                "detector": "Mean-shift"
            }
        ],
        "Anomalies": [
            {
                "Start": 1608135785.988377,
                "End": 1608136834.18396
            }
        ],
        "Number of detections": 3,
        "True Positives": [
            {
                "timestamp": 1608135820.9868429,
                "frequency": 5009730.0,
                "resistance": 408.34,
                "period": [
                    0,
                    0
                ],
                "time": "",
                "severity": "severe",
                "detector": "Expo-predict"
            },
            {
                "timestamp": 1608135900.984927,
                "frequency": 5009716.9,
                "resistance": 414.35,
                "period": [
                    0,
                    0
                ],
                "time": "",
                "severity": "severe",
                "detector": "Mean-shift"
            },
            {
                "timestamp": 1608136510.6807976,
                "frequency": 5009723.7,
                "resistance": 416.92,
                "period": [
                    0,
                    0
                ],
                "time": "",
                "severity": "severe",
                "detector": "Mean-shift"
            }
        ],
        "False Negatives": [],
        "Number of True Positives": 3,
        "Number of False Positives": 0,
        "Number of False Negatives": 0,
        "Number of True Negatives": 1,
        "Total Detection Time": 41.293811559677124,
        "Recall": 1.0,
        "Path": "/home/kimino/soft/qcm-detector/data/tests/Insertion-50ppm_chosen.csv"
    },
    "Hard-Tap-H20": {
        "Detections": [
            {
                "timestamp": 1611266741.90296,
                "frequency": 5009428.025,
                "resistance": 455.36750000000006,
                "period": [
                    0,
                    0
                ],
                "time": "",
                "severity": "severe",
                "detector": "Expo-predict"
            },
            {
                "timestamp": 1611266881.921125,
                "frequency": 5009885.875,
                "resistance": 440.71500000000003,
                "period": [
                    0,
                    0
                ],
                "time": "",
                "severity": "severe",
                "detector": "Mean-shift"
            },
            {
                "timestamp": 1611267482.0101452,
                "frequency": 5009886.9,
                "resistance": 439.055,
                "period": [
                    0,
                    0
                ],
                "time": "",
                "severity": "severe",
                "detector": "Mean-shift"
            }
        ],
        "Anomalies": [
            {
                "Start": 1611266688.3847702,
                "End": 1611268651.68291
            }
        ],
        "Number of detections": 3,
        "True Positives": [
            {
                "timestamp": 1611266741.90296,
                "frequency": 5009428.025,
                "resistance": 455.36750000000006,
                "period": [
                    0,
                    0
                ],
                "time": "",
                "severity": "severe",
                "detector": "Expo-predict"
            },
            {
                "timestamp": 1611266881.921125,
                "frequency": 5009885.875,
                "resistance": 440.71500000000003,
                "period": [
                    0,
                    0
                ],
                "time": "",
                "severity": "severe",
                "detector": "Mean-shift"
            },
            {
                "timestamp": 1611267482.0101452,
                "frequency": 5009886.9,
                "resistance": 439.055,
                "period": [
                    0,
                    0
                ],
                "time": "",
                "severity": "severe",
                "detector": "Mean-shift"
            }
        ],
        "False Negatives": [],
        "Number of True Positives": 3,
        "Number of False Positives": 0,
        "Number of False Negatives": 0,
        "Number of True Negatives": 1,
        "Total Detection Time": 75.23690962791443,
        "Recall": 1.0,
        "Path": "/home/kimino/soft/qcm-detector/data/tests/Hard-Tap-H20_chosen.csv"
    },
    "Insertion-10ppm": {
        "Detections": [
            {
                "timestamp": 1608131742.2151966,
                "frequency": 5009786.2,
                "resistance": 404.554,
                "period": [
                    0,
                    0
                ],
                "time": "",
                "severity": "severe",
                "detector": "Mean-shift"
            },
            {
                "timestamp": 1608132350.2338371,
                "frequency": 5009778.3,
                "resistance": 406.84,
                "period": [
                    0,
                    0
                ],
                "time": "",
                "severity": "severe",
                "detector": "Mean-shift"
            }
        ],
        "Anomalies": [
            {
                "Start": 1608131414.136884,
                "End": 1608132391.462955
            }
        ],
        "Number of detections": 2,
        "True Positives": [
            {
                "timestamp": 1608131742.2151966,
                "frequency": 5009786.2,
                "resistance": 404.554,
                "period": [
                    0,
                    0
                ],
                "time": "",
                "severity": "severe",
                "detector": "Mean-shift"
            },
            {
                "timestamp": 1608132350.2338371,
                "frequency": 5009778.3,
                "resistance": 406.84,
                "period": [
                    0,
                    0
                ],
                "time": "",
                "severity": "severe",
                "detector": "Mean-shift"
            }
        ],
        "False Negatives": [],
        "Number of True Positives": 2,
        "Number of False Positives": 0,
        "Number of False Negatives": 0,
        "Number of True Negatives": 1,
        "Total Detection Time": 29.852524757385254,
        "Recall": 1.0,
        "Path": "/home/kimino/soft/qcm-detector/data/tests/Insertion-10ppm_chosen.csv"
    },
    "Hard-Water-1": {
        "Detections": [
            {
                "timestamp": 1611590011.497872,
                "frequency": 5009751.933333333,
                "resistance": 435.1766666666667,
                "period": [
                    0,
                    0
                ],
                "time": "",
                "severity": "mild",
                "detector": "Expo-predict"
            }
        ],
        "Anomalies": [],
        "Number of detections": 1,
        "True Positives": [],
        "False Negatives": [],
        "Number of True Positives": 0,
        "Number of False Positives": 1,
        "Number of False Negatives": 0,
        "Number of True Negatives": 0,
        "Total Detection Time": 111.2858247756958,
        "Recall": 0,
        "Path": "/home/kimino/soft/qcm-detector/data/tests/Hard-Water-1_chosen.csv"
    },
    "Hard-Water-3": {
        "Detections": [
            {
                "timestamp": 1611861432.7637599,
                "frequency": 5009843.459999999,
                "resistance": 414.814,
                "period": [
                    0,
                    0
                ],
                "time": "",
                "severity": "mild",
                "detector": "Expo-predict"
            }
        ],
        "Anomalies": [],
        "Number of detections": 1,
        "True Positives": [],
        "False Negatives": [],
        "Number of True Positives": 0,
        "Number of False Positives": 1,
        "Number of False Negatives": 0,
        "Number of True Negatives": 0,
        "Total Detection Time": 130.9045672416687,
        "Recall": 0,
        "Path": "/home/kimino/soft/qcm-detector/data/tests/Hard-Water-3_chosen.csv"
    },
    "Hard-3ppm": {
        "Detections": [
            {
                "timestamp": 1611606652.2747,
                "frequency": 5009773.5,
                "resistance": 419.12500000000006,
                "period": [
                    0,
                    0
                ],
                "time": "",
                "severity": "severe",
                "detector": "Expo-predict"
            },
            {
                "timestamp": 1611606712.274875,
                "frequency": 5009841.3,
                "resistance": 442.78,
                "period": [
                    0,
                    0
                ],
                "time": "",
                "severity": "mild",
                "detector": "Expo-predict"
            },
            {
                "timestamp": 1611607002.275425,
                "frequency": 5009838.0,
                "resistance": 450.525,
                "period": [
                    0,
                    0
                ],
                "time": "",
                "severity": "severe",
                "detector": "Mean-shift"
            },
            {
                "timestamp": 1611607602.2771,
                "frequency": 5009836.45,
                "resistance": 453.9625,
                "period": [
                    0,
                    0
                ],
                "time": "",
                "severity": "severe",
                "detector": "Mean-shift"
            }
        ],
        "Anomalies": [
            {
                "Start": 1611606633.7742999,
                "End": 1611608694.7772002
            }
        ],
        "Number of detections": 4,
        "True Positives": [
            {
                "timestamp": 1611606652.2747,
                "frequency": 5009773.5,
                "resistance": 419.12500000000006,
                "period": [
                    0,
                    0
                ],
                "time": "",
                "severity": "severe",
                "detector": "Expo-predict"
            },
            {
                "timestamp": 1611606712.274875,
                "frequency": 5009841.3,
                "resistance": 442.78,
                "period": [
                    0,
                    0
                ],
                "time": "",
                "severity": "mild",
                "detector": "Expo-predict"
            },
            {
                "timestamp": 1611607002.275425,
                "frequency": 5009838.0,
                "resistance": 450.525,
                "period": [
                    0,
                    0
                ],
                "time": "",
                "severity": "severe",
                "detector": "Mean-shift"
            },
            {
                "timestamp": 1611607602.2771,
                "frequency": 5009836.45,
                "resistance": 453.9625,
                "period": [
                    0,
                    0
                ],
                "time": "",
                "severity": "severe",
                "detector": "Mean-shift"
            }
        ],
        "False Negatives": [],
        "Number of True Positives": 4,
        "Number of False Positives": 0,
        "Number of False Negatives": 0,
        "Number of True Negatives": 1,
        "Total Detection Time": 84.46705198287964,
        "Recall": 1.0,
        "Path": "/home/kimino/soft/qcm-detector/data/tests/Hard-3ppm_chosen.csv"
    },
    "Insertion-3ppm": {
        "Detections": [
            {
                "timestamp": 1608128222.836986,
                "frequency": 5009834.6,
                "resistance": 398.19,
                "period": [
                    0,
                    0
                ],
                "time": "",
                "severity": "severe",
                "detector": "Mean-shift"
            }
        ],
        "Anomalies": [
            {
                "Start": 1608127834.843526,
                "End": 1608128678.820218
            }
        ],
        "Number of detections": 1,
        "True Positives": [
            {
                "timestamp": 1608128222.836986,
                "frequency": 5009834.6,
                "resistance": 398.19,
                "period": [
                    0,
                    0
                ],
                "time": "",
                "severity": "severe",
                "detector": "Mean-shift"
            }
        ],
        "False Negatives": [],
        "Number of True Positives": 1,
        "Number of False Positives": 0,
        "Number of False Negatives": 0,
        "Number of True Negatives": 1,
        "Total Detection Time": 30.24501371383667,
        "Recall": 1.0,
        "Path": "/home/kimino/soft/qcm-detector/data/tests/Insertion-3ppm_chosen.csv"
    },
    "Insertion-100ppm": {
        "Detections": [
            {
                "timestamp": 1608138070.6195803,
                "frequency": 5009687.3,
                "resistance": 401.615,
                "period": [
                    0,
                    0
                ],
                "time": "",
                "severity": "severe",
                "detector": "Expo-predict"
            },
            {
                "timestamp": 1608138230.6190987,
                "frequency": 5009711.9,
                "resistance": 419.445,
                "period": [
                    0,
                    0
                ],
                "time": "",
                "severity": "severe",
                "detector": "Mean-shift"
            },
            {
                "timestamp": 1608138840.503684,
                "frequency": 5009711.5,
                "resistance": 422.26,
                "period": [
                    0,
                    0
                ],
                "time": "",
                "severity": "severe",
                "detector": "Mean-shift"
            }
        ],
        "Anomalies": [
            {
                "Start": 1608138031.120696,
                "End": 1608139140.5116959
            }
        ],
        "Number of detections": 3,
        "True Positives": [
            {
                "timestamp": 1608138070.6195803,
                "frequency": 5009687.3,
                "resistance": 401.615,
                "period": [
                    0,
                    0
                ],
                "time": "",
                "severity": "severe",
                "detector": "Expo-predict"
            },
            {
                "timestamp": 1608138230.6190987,
                "frequency": 5009711.9,
                "resistance": 419.445,
                "period": [
                    0,
                    0
                ],
                "time": "",
                "severity": "severe",
                "detector": "Mean-shift"
            },
            {
                "timestamp": 1608138840.503684,
                "frequency": 5009711.5,
                "resistance": 422.26,
                "period": [
                    0,
                    0
                ],
                "time": "",
                "severity": "severe",
                "detector": "Mean-shift"
            }
        ],
        "False Negatives": [],
        "Number of True Positives": 3,
        "Number of False Positives": 0,
        "Number of False Negatives": 0,
        "Number of True Negatives": 1,
        "Total Detection Time": 41.47671437263489,
        "Recall": 1.0,
        "Path": "/home/kimino/soft/qcm-detector/data/tests/Insertion-100ppm_chosen.csv"
    },
    "Hard-Water-2": {
        "Detections": [],
        "Anomalies": [],
        "Number of detections": 0,
        "True Positives": [],
        "False Negatives": [],
        "Number of True Positives": 0,
        "Number of False Positives": 0,
        "Number of False Negatives": 0,
        "Number of True Negatives": 0,
        "Total Detection Time": 177.1878092288971,
        "Recall": 0,
        "Path": "/home/kimino/soft/qcm-detector/data/tests/Hard-Water-2_chosen.csv"
    }
}